Metadata-Version: 2.4
Name: iflow-mcp_kukapay_modbus-mcp
Version: 0.1.0
Summary: An MCP server that standardizes and contextualizes Modbus data, enabling seamless integration of AI agents with industrial IoT systems.e
License-File: LICENSE
Requires-Python: >=3.10
Requires-Dist: mcp[cli]>=1.6.0
Requires-Dist: pymodbus>=3.9.2
Requires-Dist: python-dotenv>=1.1.0
